AUTHORS.rst
CONTRIBUTING.rst
HISTORY.rst
MANIFEST.in
README.rst
setup.cfg
setup.py
docs/Makefile
docs/authors.rst
docs/conf.py
docs/contributing.rst
docs/faq.rst
docs/features.rst
docs/history.rst
docs/index.rst
docs/installation.rst
docs/make.bat
docs/modules.rst
docs/readme.rst
docs/wbuild.rst
docs/_build/html/_images/HTML_output_demo.png
docs/_build/html/_images/snakemake_wbuild_diag_build.jpg
docs/_build/html/_images/snakemake_wbuild_diag_setup.jpg
docs/_build/html/_static/ajax-loader.gif
docs/_build/html/_static/comment-bright.png
docs/_build/html/_static/comment-close.png
docs/_build/html/_static/comment.png
docs/_build/html/_static/down-pressed.png
docs/_build/html/_static/down.png
docs/_build/html/_static/file.png
docs/_build/html/_static/minus.png
docs/_build/html/_static/plus.png
docs/_build/html/_static/up-pressed.png
docs/_build/html/_static/up.png
docs/res/images/HTML_output_demo.png
docs/res/images/snakemake_wbuild_diag.jpg
docs/res/images/snakemake_wbuild_diag_build.jpg
docs/res/images/snakemake_wbuild_diag_setup.jpg
tests/__init__.py
tests/test_cli.py
tests/test_util.py
wbuild/__init__.py
wbuild/autolink.py
wbuild/cli.py
wbuild/createIndex.py
wbuild/scanFiles.py
wbuild/utils.py
wbuild/wBuild.snakefile
wbuild.egg-info/PKG-INFO
wbuild.egg-info/SOURCES.txt
wbuild.egg-info/dependency_links.txt
wbuild.egg-info/entry_points.txt
wbuild.egg-info/not-zip-safe
wbuild.egg-info/requires.txt
wbuild.egg-info/top_level.txt
wbuild/.wBuild/wBuildParser.R
wbuild/.wBuild/wBuildParser2.R
wbuild/.wBuild/wbParse.py
wbuild/R/installRpackages.R
wbuild/R/render_child.R
wbuild/R/rmarkdown_show_hide_table.R
wbuild/R/wBRender.R
wbuild/R/wBSMDump.R
wbuild/__pycache__/__init__.cpython-35.pyc
wbuild/__pycache__/autolink.cpython-35.pyc
wbuild/__pycache__/cli.cpython-35.pyc
wbuild/__pycache__/createIndex.cpython-35.pyc
wbuild/__pycache__/scanFiles.cpython-35.pyc
wbuild/__pycache__/utils.cpython-35.pyc
wbuild/demo/Snakefile
wbuild/demo/readme.md
wbuild/demo/Data/ids.txt
wbuild/demo/Data/Analysis1/iris.RDS
wbuild/demo/Scripts/Analysis1/010_BasicInput/010_Readme.md
wbuild/demo/Scripts/Analysis1/010_BasicInput/020_BasicInput.R
wbuild/demo/Scripts/Analysis1/020_InputOutput/010_Readme.md
