Metadata-Version: 2.1
Name: wbuild
Version: 1.8.0
Summary: Automatic build tool for R Reports
Home-page: https://github.com/gagneurlab/wBuild
Author: Leonhard Wachutka
Author-email: leonhard@wachutka.eu
License: UNKNOWN
Keywords: wbuild
Platform: UNKNOWN
Classifier: Intended Audience :: Developers
Classifier: Natural Language :: English
Classifier: Programming Language :: Python :: 3
Classifier: Programming Language :: Python :: 3.6
Classifier: Programming Language :: Python :: 3.7
Classifier: Programming Language :: Python :: 3.8
